openeurotop/__init__.py
openeurotop/case_studies.py
openeurotop/constants.py
openeurotop/exceptions.py
openeurotop/neural_network.py
openeurotop/neural_network_clash.py
openeurotop/overtopping.py
openeurotop/probabilistic.py
openeurotop/reduction_factors.py
openeurotop/run_up.py
openeurotop/special_cases.py
openeurotop/validation.py
openeurotop/wave_parameters.py
openeurotop/xgboost_model.py
openeurotop-1.0.0.dist-info/licenses/LICENSE
openeurotop-1.0.0.dist-info/METADATA
openeurotop-1.0.0.dist-info/WHEEL
openeurotop-1.0.0.dist-info/top_level.txt
openeurotop-1.0.0.dist-info/RECORD
