Metadata-Version: 2.4
Name: openeurotop
Version: 1.0.0
Summary: Implémentation Python du guide EurOtop pour le calcul du franchissement de vagues
Home-page: https://github.com/Pavlishenku/OpenEurOtop
Author: OpenEurOtop Contributors
Author-email: OpenEurOtop Contributors <pavlishenku@gmail.com>
Maintainer-email: OpenEurOtop Contributors <pavlishenku@gmail.com>
License: MIT
Project-URL: Homepage, https://github.com/Pavlishenku/OpenEurOtop
Project-URL: Documentation, https://openeurotop.readthedocs.io/
Project-URL: Repository, https://github.com/Pavlishenku/OpenEurOtop
Project-URL: Bug Tracker, https://github.com/Pavlishenku/OpenEurOtop/issues
Keywords: eurotop,wave,overtopping,coastal,engineering,hydraulics
Classifier: Development Status :: 5 - Production/Stable
Classifier: Intended Audience :: Science/Research
Classifier: Intended Audience :: Developers
Classifier: Topic :: Scientific/Engineering
Classifier: Topic :: Scientific/Engineering :: Physics
Classifier: Topic :: Scientific/Engineering :: Hydrology
Classifier: License :: OSI Approved :: MIT License
Classifier: Programming Language :: Python :: 3
Classifier: Programming Language :: Python :: 3.8
Classifier: Programming Language :: Python :: 3.9
Classifier: Programming Language :: Python :: 3.10
Classifier: Programming Language :: Python :: 3.11
Classifier: Programming Language :: Python :: 3.12
Classifier: Operating System :: OS Independent
Requires-Python: >=3.8
License-File: LICENSE
Requires-Dist: numpy>=1.20.0
Requires-Dist: scipy>=1.7.0
Provides-Extra: dev
Requires-Dist: pytest>=6.0; extra == "dev"
Requires-Dist: pytest-cov>=2.0; extra == "dev"
Requires-Dist: black>=21.0; extra == "dev"
Requires-Dist: flake8>=3.9; extra == "dev"
Requires-Dist: sphinx>=4.0; extra == "dev"
Requires-Dist: sphinx-rtd-theme>=1.0; extra == "dev"
Provides-Extra: ml
Requires-Dist: scikit-learn>=1.0.0; extra == "ml"
Requires-Dist: xgboost>=1.5.0; extra == "ml"
Requires-Dist: tensorflow>=2.8.0; extra == "ml"
Provides-Extra: all
Requires-Dist: pytest>=6.0; extra == "all"
Requires-Dist: pytest-cov>=2.0; extra == "all"
Requires-Dist: black>=21.0; extra == "all"
Requires-Dist: flake8>=3.9; extra == "all"
Requires-Dist: sphinx>=4.0; extra == "all"
Requires-Dist: sphinx-rtd-theme>=1.0; extra == "all"
Requires-Dist: scikit-learn>=1.0.0; extra == "all"
Requires-Dist: xgboost>=1.5.0; extra == "all"
Requires-Dist: tensorflow>=2.8.0; extra == "all"
Dynamic: author
Dynamic: home-page
Dynamic: license-file
Dynamic: requires-python
